coshiota/__init__.py
coshiota/certificate.py
coshiota/cryptography_lowlevel.py
coshiota/csv_tools.py
coshiota/linux_kernel.py
coshiota/naming.py
coshiota/serial_number.py
coshiota/tools.py
coshiota/trusty_payload_message.py
coshiota-0.3.1.dist-info/METADATA
coshiota-0.3.1.dist-info/WHEEL
coshiota-0.3.1.dist-info/licenses/COPYING.txt
coshiota-0.3.1.dist-info/RECORD
