Metadata-Version: 2.4
Name: coshiota
Version: 0.3.1
Author-email: doubleO8 <wb008@hdm-stuttgart.de>
License-Expression: GPL-2.0-only
License-File: COPYING.txt
Requires-Python: >=3.9.2
Requires-Dist: cryptography~=45.0.4
Requires-Dist: orjson~=3.10.18
Requires-Dist: pendulum!=3.0.0,>=2.1.2
Requires-Dist: pydantic~=1.10.13
